brewmind/__init__.py
chicory_cli/__init__.py
chicory_cli/__main__.py
chicory_cli/clidriver.py
chicory_cli/commands/__init__.py
chicory_cli/commands/create.py
chicory_cli/commands/feature.py
chicory_cli/commands/prepare.py
chicory_cli/tools/__init__.py
chicory_cli/tools/utilities.py
chicory_tools/__init__.py
chicory_tools/api_config.py
chicory_tools/aws.py
chicory_tools/cli.py
chicory_tools/db.py
chicory_tools/metadata.py
chicory_tools/neo4j_heap.py
chicory_tools/s3.py
services/__init__.py
services/main.py
services/chains/__init__.py
services/chains/platform_graph_chain.py
services/data_explorer/__init__.py
services/data_explorer/const.py
services/data_explorer/di_selector.py
services/data_explorer/dw_planner.py
services/data_explorer/dw_planner_running.py
services/data_explorer/tools.py
services/feature_brew/__init__.py
services/feature_brew/featureset_agent.py
services/feature_brew/components/__init__.py
services/feature_brew/components/dataset.py
services/feature_brew/components/sklearn_wrapper.py
services/feature_brew/components/store.py
services/feature_brew/components/training.py
services/feature_brew/components/validate.py
services/models/__init__.py
services/models/sql_gen_query.py
services/ni-data_scanner/__init__.py
services/ni-feature_brew/__init__.py
services/sql_generator/__init__.py
services/sql_generator/const.py
services/sql_generator/utils.py
services/sql_generator/agents/__init__.py
services/sql_generator/agents/base.py
services/sql_generator/agents/chat_manager.py
services/sql_generator/agents/decomposer.py
services/sql_generator/agents/refiner.py
services/sql_generator/agents/selector.py
services/sql_generator/tools/__init__.py
services/sql_generator/tools/api_config.py
services/sql_generator/tools/databaseconnector.py
services/sql_generator/tools/llm.py
utils/__init__.py
utils/async_utils.py
utils/helper.py
featurebrew-0.0.1b2.dist-info/LICENSE.txt
featurebrew-0.0.1b2.dist-info/METADATA
featurebrew-0.0.1b2.dist-info/WHEEL
featurebrew-0.0.1b2.dist-info/entry_points.txt
featurebrew-0.0.1b2.dist-info/top_level.txt
featurebrew-0.0.1b2.dist-info/RECORD
