Metadata-Version: 2.1
Name: featurebrew
Version: 0.0.1b2
Summary: Universal Command Line Environment for Chicory.
Home-page: http://chicory.ai
Author: Chicory.AI
License: Apache License 2.0
Requires-Python: >= 3.9
License-File: LICENSE.txt
Requires-Dist: click ==8.1.7
Requires-Dist: PyYAML ==6.0.1
Requires-Dist: asyncio ==3.4.3
Requires-Dist: boto3 ==1.34.132
Requires-Dist: chromadb ==0.4.24
Requires-Dist: fastapi ==0.110.1
Requires-Dist: langchain ==0.2.1
Requires-Dist: langchain-openai ==0.1.8
Requires-Dist: langchainhub ==0.1.17
Requires-Dist: langchain-experimental ==0.0.59
Requires-Dist: langgraph ==0.0.60
Requires-Dist: langsmith ==0.1.67
Requires-Dist: neo4j ==5.19.0
Requires-Dist: numpy ==1.26.4
Requires-Dist: openai ==1.30.5
Requires-Dist: opentelemetry-api ==1.24.0
Requires-Dist: pandas ==2.2.2
Requires-Dist: pydantic ==2.7.0
Requires-Dist: uvicorn ==0.29.0
Requires-Dist: python-docx ==1.1.0
Requires-Dist: python-dotenv ==1.0.1
Requires-Dist: psycopg2-binary ==2.9.9
Requires-Dist: google-cloud-bigquery ==3.24.0
Requires-Dist: func-timeout ==4.3.5
Requires-Dist: torch ==2.3.0
Requires-Dist: scikit-learn ==1.4.2
Requires-Dist: openai-multi-tool-use-parallel-patch ==0.2.0
